onlykey_agent/__init__.py
onlykey_agent/__main__.py
onlykey_agent/client.py
onlykey_agent/formats.py
onlykey_agent/protocol.py
onlykey_agent/server.py
onlykey_agent/util.py
onlykey_agent-1.0.0.dist-info/LICENSE
onlykey_agent-1.0.0.dist-info/METADATA
onlykey_agent-1.0.0.dist-info/WHEEL
onlykey_agent-1.0.0.dist-info/entry_points.txt
onlykey_agent-1.0.0.dist-info/top_level.txt
onlykey_agent-1.0.0.dist-info/RECORD
