Metadata-Version: 2.1
Name: onlykey-agent
Version: 1.0.0
Summary: Using OnlyKey as hardware SSH agent
Home-page: http://github.com/trustcrypto/onlykey-agent
Author: CryptoTrust
Author-email: admin@crp.to
License: UNKNOWN
Platform: POSIX
Classifier: Environment :: Console
Classifier: Development Status :: 5 - Production/Stable
Classifier: Intended Audience :: Developers
Classifier: Intended Audience :: Information Technology
Classifier: Intended Audience :: System Administrators
Classifier: License :: OSI Approved :: GNU Lesser General Public License v3 (LGPLv3)
Classifier: Operating System :: POSIX
Classifier: Programming Language :: Python :: 2.7
Classifier: Programming Language :: Python :: 3.4
Classifier: Topic :: Software Development :: Libraries :: Python Modules
Classifier: Topic :: System :: Networking
Classifier: Topic :: Communications
Classifier: Topic :: Security
Classifier: Topic :: Utilities
Requires-Dist: ecdsa (>=0.13)
Requires-Dist: ed25519 (>=1.4)
Requires-Dist: Cython (>=0.23.4)
Requires-Dist: protobuf (>=2.6.1)
Requires-Dist: semver (>=2.2)
